pnpq/__init__.py
pnpq/errors.py
pnpq/events.py
pnpq/py.typed
pnpq/stub_util.py
pnpq/units.py
pnpq/apt/__init__.py
pnpq/apt/connection.py
pnpq/apt/protocol.py
pnpq/devices/__init__.py
pnpq/devices/odl_ozoptics_650ml.py
pnpq/devices/odl_thorlabs_kbd101.py
pnpq/devices/odl_thorlabs_kbd101_stub.py
pnpq/devices/polarization_controller_thorlabs_mpc.py
pnpq/devices/polarization_controller_thorlabs_mpc_stub.py
pnpq/devices/switch_thorlabs_osw_e.py
pnpq/devices/switch_thorlabs_osw_e_stub.py
pnpq/devices/utils.py
pnpq/devices/waveplate_thorlabs_k10cr1.py
pnpq/devices/waveplate_thorlabs_k10cr1_stub.py
pnpq-0.2.0.dist-info/METADATA
pnpq-0.2.0.dist-info/WHEEL
pnpq-0.2.0.dist-info/licenses/LICENSE.md
pnpq-0.2.0.dist-info/RECORD
