Metadata-Version: 2.4
Name: pnpq
Version: 0.2.0
Summary: Python library for laboratory devices often used in quantum networking and computing testbeds.
Project-URL: homepage, https://github.com/moonshot-nagayama-pj/PnPQ
Project-URL: source, https://github.com/moonshot-nagayama-pj/PnPQ
Project-URL: changelog, https://github.com/moonshot-nagayama-pj/PnPQ/releases
Project-URL: releasenotes, https://github.com/moonshot-nagayama-pj/PnPQ/releases
Project-URL: documentation, https://moonshot-nagayama-pj.github.io/PnPQ/
Project-URL: issues, https://github.com/moonshot-nagayama-pj/PnPQ/issues
Author-email: Amin Taherkhani <amin@sfc.wide.ad.jp>, Andrew Todd <at@auspicacious.org>, Lars Matsumiya <larsmatsumiya@gmail.com>, Tom Shen <tomshen@keio.jp>
License-Expression: BSD-3-Clause
License-File: LICENSE.md
Keywords: optics,ozoptics,physics,quantum,thorlabs
Classifier: Development Status :: 4 - Beta
Classifier: Intended Audience :: Science/Research
Classifier: License :: OSI Approved :: BSD License
Classifier: Operating System :: OS Independent
Classifier: Programming Language :: Python :: 3.13
Classifier: Programming Language :: Python :: 3.14
Classifier: Programming Language :: Python :: 3.15
Classifier: Topic :: Scientific/Engineering
Classifier: Topic :: Scientific/Engineering :: Physics
Classifier: Topic :: Scientific/Engineering :: Quantum Computing
Classifier: Topic :: Software Development :: Libraries
Classifier: Topic :: Software Development :: Libraries :: Python Modules
Classifier: Typing :: Typed
Requires-Python: >=3.13
Requires-Dist: pint>=0.24.3
Requires-Dist: pyserial>=3.5
Requires-Dist: structlog>=24.4.0
Requires-Dist: types-pyserial>=3.5.0.20240826
